PDFCode/PDFCode.py
PDFCode/__init__.py
PDFCode-0.1.2.1.dist-info/LICENSE
PDFCode-0.1.2.1.dist-info/METADATA
PDFCode-0.1.2.1.dist-info/WHEEL
PDFCode-0.1.2.1.dist-info/entry_points.txt
PDFCode-0.1.2.1.dist-info/top_level.txt
PDFCode-0.1.2.1.dist-info/RECORD
