Metadata-Version: 2.1
Name: PDFCode
Version: 0.1.2.1
Summary: Save code files into PDF format with syntax highlighting.
Home-page: https://github.com/xincoder/PDFCode
Author: xincoder
Author-email: xincoder@gmail.com
License: UNKNOWN
Platform: UNKNOWN
Classifier: Programming Language :: Python :: 3.6
Classifier: License :: OSI Approved :: MIT License
Classifier: Operating System :: OS Independent
Requires-Python: >=2.7
Requires-Dist: pygments
Requires-Dist: pdfkit
Requires-Dist: file-magic
Requires-Dist: markdown
